delphai_search_utils/__init__.py
delphai_search_utils/data/demonyms.truecasemodel
delphai_search_utils/elastic_query.py
delphai_search_utils/query.py
delphai_search_utils/tests/__init__.py
delphai_search_utils/tests/test_text_query.py
delphai_search_utils/tests/test_utils.py
delphai_search_utils/text_query.py
delphai_search_utils/utils.py
delphai_search_utils-0.2.1.dist-info/METADATA
delphai_search_utils-0.2.1.dist-info/WHEEL
delphai_search_utils-0.2.1.dist-info/RECORD
